{
  "_format": "hh-sol-cache-2",
  "files": {
    "C:\\Users\\DELL\\Desktop\\NFT-Wallet\\contracts\\guardian.sol": {
      "lastModificationDate": 1737108443104,
      "contentHash": "507ec32764045752a06b03a99f80da18",
      "sourceName": "contracts/guardian.sol",
      "solcConfig": {
        "version": "0.8.20",
        "settings": {
          "evmVersion": "paris",
          "optimizer": {
            "enabled": false,
            "runs": 200
          },
          "outputSelection": {
            "*": {
              "*": [
                "abi",
                "evm.bytecode",
                "evm.deployedBytecode",
                "evm.methodIdentifiers",
                "metadata"
              ],
              "": [
                "ast"
              ]
            }
          }
        }
      },
      "imports": [],
      "versionPragmas": [
        "^0.8.19"
      ],
      "artifacts": [
        "AdvancedSafeWithTokenbound",
        "ITokenboundAccount"
      ]
    },
    "C:\\Users\\DELL\\Desktop\\NFT-Wallet\\contracts\\MultiSignature.sol": {
      "lastModificationDate": 1737111484754,
      "contentHash": "75b31289fbd102b4580eef79a1010412",
      "sourceName": "contracts/MultiSignature.sol",
      "solcConfig": {
        "version": "0.8.20",
        "settings": {
          "evmVersion": "paris",
          "optimizer": {
            "enabled": false,
            "runs": 200
          },
          "outputSelection": {
            "*": {
              "*": [
                "abi",
                "evm.bytecode",
                "evm.deployedBytecode",
                "evm.methodIdentifiers",
                "metadata"
              ],
              "": [
                "ast"
              ]
            }
          }
        }
      },
      "imports": [
        "contracts/guardian.sol",
        "@openzeppelin/contracts/access/Ownable.sol"
      ],
      "versionPragmas": [
        ">=0.7.0 <0.9.0"
      ],
      "artifacts": [
        "MultiSigWallet"
      ]
    },
    "C:\\Users\\DELL\\Desktop\\NFT-Wallet\\node_modules\\@openzeppelin\\contracts\\access\\Ownable.sol": {
      "lastModificationDate": 1736875455577,
      "contentHash": "d3c790edc9ccf808a17c5a6cd13614fd",
      "sourceName": "@openzeppelin/contracts/access/Ownable.sol",
      "solcConfig": {
        "version": "0.8.20",
        "settings": {
          "evmVersion": "paris",
          "optimizer": {
            "enabled": false,
            "runs": 200
          },
          "outputSelection": {
            "*": {
              "*": [
                "abi",
                "evm.bytecode",
                "evm.deployedBytecode",
                "evm.methodIdentifiers",
                "metadata"
              ],
              "": [
                "ast"
              ]
            }
          }
        }
      },
      "imports": [
        "../utils/Context.sol"
      ],
      "versionPragmas": [
        "^0.8.20"
      ],
      "artifacts": [
        "Ownable"
      ]
    },
    "C:\\Users\\DELL\\Desktop\\NFT-Wallet\\node_modules\\@openzeppelin\\contracts\\utils\\Context.sol": {
      "lastModificationDate": 1736875454859,
      "contentHash": "67bfbc07588eb8683b3fd8f6f909563e",
      "sourceName": "@openzeppelin/contracts/utils/Context.sol",
      "solcConfig": {
        "version": "0.8.20",
        "settings": {
          "evmVersion": "paris",
          "optimizer": {
            "enabled": false,
            "runs": 200
          },
          "outputSelection": {
            "*": {
              "*": [
                "abi",
                "evm.bytecode",
                "evm.deployedBytecode",
                "evm.methodIdentifiers",
                "metadata"
              ],
              "": [
                "ast"
              ]
            }
          }
        }
      },
      "imports": [],
      "versionPragmas": [
        "^0.8.20"
      ],
      "artifacts": [
        "Context"
      ]
    },
    "C:\\Users\\DELL\\Desktop\\NFT-Wallet\\contracts\\Lock.sol": {
      "lastModificationDate": 1737111805382,
      "contentHash": "d41d8cd98f00b204e9800998ecf8427e",
      "sourceName": "contracts/Lock.sol",
      "solcConfig": {
        "version": "0.8.20",
        "settings": {
          "evmVersion": "paris",
          "optimizer": {
            "enabled": false,
            "runs": 200
          },
          "outputSelection": {
            "*": {
              "*": [
                "abi",
                "evm.bytecode",
                "evm.deployedBytecode",
                "evm.methodIdentifiers",
                "metadata"
              ],
              "": [
                "ast"
              ]
            }
          }
        }
      },
      "imports": [],
      "versionPragmas": [],
      "artifacts": []
    },
    "C:\\Users\\DELL\\Desktop\\NFT-Wallet\\contracts\\USDTOrderBook.sol": {
      "lastModificationDate": 1737108443104,
      "contentHash": "129459956a7f3d148c745ac51ce8aa62",
      "sourceName": "contracts/USDTOrderBook.sol",
      "solcConfig": {
        "version": "0.8.20",
        "settings": {
          "evmVersion": "paris",
          "optimizer": {
            "enabled": false,
            "runs": 200
          },
          "outputSelection": {
            "*": {
              "*": [
                "abi",
                "evm.bytecode",
                "evm.deployedBytecode",
                "evm.methodIdentifiers",
                "metadata"
              ],
              "": [
                "ast"
              ]
            }
          }
        }
      },
      "imports": [],
      "versionPragmas": [
        "^0.8.0"
      ],
      "artifacts": [
        "OrderBook"
      ]
    }
  }
}
